ts1/__init__.py
ts1/http2.py
ts1/signature.py
ts1/tls.py
ts1/utils.py
ts1_signatures-0.1.6.dist-info/LICENSE
ts1_signatures-0.1.6.dist-info/METADATA
ts1_signatures-0.1.6.dist-info/WHEEL
ts1_signatures-0.1.6.dist-info/top_level.txt
ts1_signatures-0.1.6.dist-info/RECORD
