Metadata-Version: 2.1
Name: ts1-signatures
Version: 0.1.6
Summary: TLS and HTTP signature and fingerprint library
Home-page: https://github.com/lwthiker/ts1
Author: lwthiker
Author-email: lwt@lwthiker.com
Project-URL: Bug Tracker, https://github.com/lwthiker/ts1/issues
Classifier: Programming Language :: Python :: 3
Classifier: License :: OSI Approved :: MIT License
Classifier: Operating System :: OS Independent
Requires-Python: >=3.2
License-File: LICENSE
Requires-Dist: dpkt
